[{"id":"d0b02d8f.2de5a","type":"tab","label":"Lab 03","disabled":false,"info":""},{"id":"f8db4422.79ced8","type":"mongodb","z":"","hostname":"127.0.0.1","port":"27017","db":"test","name":""},{"id":"9979d92e.2e1ad","type":"websocket-listener","z":"","path":"/acc","wholemsg":"false"},{"id":"bcffa65c.274ee","type":"mqtt-broker","z":"","name":"","broker":"192.168.43.136","port":"1883","clientid":"","usetls":false,"compatmode":true,"keepalive":"60","cleansession":true,"birthTopic":"","birthQos":"0","birthPayload":"","closeTopic":"","closeQos":"0","closePayload":"","willTopic":"","willQos":"0","willPayload":""},{"id":"9415cdfb.d5ca1","type":"websocket-client","z":"","path":"/acc","tls":"","wholemsg":"false"},{"id":"89f8da3f.c20c","type":"mongodb out","z":"d0b02d8f.2de5a","mongodb":"f8db4422.79ced8","name":"","collection":"acc","payonly":true,"upsert":false,"multi":false,"operation":"insert","x":470,"y":80,"wires":[]},{"id":"8e902ed6.99b068","type":"websocket out","z":"d0b02d8f.2de5a","name":"","server":"","client":"9415cdfb.d5ca1","x":420,"y":140,"wires":[]},{"id":"8388de55.daa218","type":"mqtt in","z":"d0b02d8f.2de5a","name":"","topic":"acc","qos":"2","broker":"bcffa65c.274ee","x":80,"y":140,"wires":[["5056081f.2a9ee"]]},{"id":"5056081f.2a9ee","type":"function","z":"d0b02d8f.2de5a","name":"","func":"var date = new Date();\nmsg.payload = {acc: msg.payload, date: date.toISOString()};\nreturn msg;","outputs":1,"noerr":0,"x":230,"y":140,"wires":[["89f8da3f.c20c","8e902ed6.99b068","2972289f.7ab438"]]},{"id":"2972289f.7ab438","type":"debug","z":"d0b02d8f.2de5a","name":"","active":true,"tosidebar":true,"console":false,"tostatus":false,"complete":"false","x":430,"y":200,"wires":[]}]